dummy_thumbnails/__init__.py
dummy_thumbnails/apps.py
dummy_thumbnails/base.py
dummy_thumbnails/conf.py
dummy_thumbnails/defaults.py
dummy_thumbnails/helpers.py
dummy_thumbnails/settings.py
dummy_thumbnails/contrib/__init__.py
dummy_thumbnails/contrib/image_importers/__init__.py
dummy_thumbnails/contrib/image_importers/feed/__init__.py
dummy_thumbnails/contrib/image_importers/feed/apps.py
dummy_thumbnails/contrib/image_importers/feed/conf.py
dummy_thumbnails/contrib/image_importers/feed/defaults.py
dummy_thumbnails/contrib/image_importers/feed/reader.py
dummy_thumbnails/contrib/image_importers/feed/settings.py
dummy_thumbnails/contrib/image_importers/feed/management/__init__.py
dummy_thumbnails/contrib/image_importers/feed/management/commands/__init__.py
dummy_thumbnails/contrib/image_importers/feed/management/commands/dummy_thumbnails_import_from_feed.py
dummy_thumbnails/contrib/thumbnailers/__init__.py
dummy_thumbnails/contrib/thumbnailers/django_imagekit/__init__.py
dummy_thumbnails/contrib/thumbnailers/django_imagekit/generatorlibrary.py
dummy_thumbnails/contrib/thumbnailers/easy_thumbnails/__init__.py
dummy_thumbnails/contrib/thumbnailers/easy_thumbnails/source_generators.py
dummy_thumbnails/contrib/thumbnailers/sorl_thumbnail/__init__.py
dummy_thumbnails/contrib/thumbnailers/sorl_thumbnail/engines/__init__.py
dummy_thumbnails/contrib/thumbnailers/sorl_thumbnail/engines/dummy_engine.py
dummy_thumbnails/management/__init__.py
dummy_thumbnails/management/commands/__init__.py
dummy_thumbnails/management/commands/dummy_thumbnails_symlink_dummy_images.py
dummy_thumbnails/management/commands/dummy_thumbnails_verify_dummy_images.py
dummy_thumbnails/static/dummy_thumbnails/images/README.rst
dummy_thumbnails/static/dummy_thumbnails/images/mixed/1-1208707554nqU5.jpg
dummy_thumbnails/static/dummy_thumbnails/images/mixed/1-1226265697kzA8.jpg
dummy_thumbnails/static/dummy_thumbnails/images/mixed/1-12313172492sOG.jpg
django_dummy_thumbnails-0.2.5.dist-info/LICENSE_GPL2.0.txt
django_dummy_thumbnails-0.2.5.dist-info/LICENSE_LGPL_2.1.txt
django_dummy_thumbnails-0.2.5.dist-info/METADATA
django_dummy_thumbnails-0.2.5.dist-info/WHEEL
django_dummy_thumbnails-0.2.5.dist-info/top_level.txt
django_dummy_thumbnails-0.2.5.dist-info/RECORD
