Metadata-Version: 2.1
Name: django-dummy-thumbnails
Version: 0.2.5
Summary: Dummy thumbnails for most popular Django thumbnail generators.
Home-page: https://github.com/barseghyanartur/django-dummy-thumbnails/
Author: Artur Barseghyan
Author-email: artur.barseghyan@gmail.com
License: GPL-2.0-only OR LGPL-2.1-or-later
Keywords: django,django-dummy-thumbnails
Platform: UNKNOWN
Classifier: Programming Language :: Python :: 2.7
Classifier: Programming Language :: Python :: 3.5
Classifier: Programming Language :: Python :: 3.6
Classifier: Programming Language :: Python :: 3.7
Classifier: Environment :: Web Environment
Classifier: License :: OSI Approved :: GNU General Public License v2 (GPLv2)
Classifier: License :: OSI Approved :: GNU Lesser General Public License v2 or later (LGPLv2+)
Classifier: Framework :: Django
Classifier: Intended Audience :: Developers
Classifier: Operating System :: OS Independent
Classifier: Development Status :: 4 - Beta
Requires-Dist: six (>=1.4.1)
Requires-Dist: django-nine (>=0.2.2)
Requires-Dist: django-eximagination (>=0.8)
Requires-Dist: feedparser
